chatgpt_app/__init__.py
chatgpt_app/a.txt
chatgpt_app-0.0.1.dist-info/licenses/LICENSE
chatgpt_app-0.0.1.dist-info/METADATA
chatgpt_app-0.0.1.dist-info/WHEEL
chatgpt_app-0.0.1.dist-info/top_level.txt
chatgpt_app-0.0.1.dist-info/RECORD
